pytest_integration_mark/__init__.py
pytest_integration_mark/hooks.py
pytest_integration_mark-0.2.0.dist-info/LICENSE
pytest_integration_mark-0.2.0.dist-info/METADATA
pytest_integration_mark-0.2.0.dist-info/WHEEL
pytest_integration_mark-0.2.0.dist-info/entry_points.txt
pytest_integration_mark-0.2.0.dist-info/RECORD
