Metadata-Version: 2.1
Name: pytest-integration-mark
Version: 0.2.0
Summary: Automatic integration test marking and excluding plugin for pytest
Home-page: https://github.com/Barbora-Data-Science/pytest-integration-mark
License: Apache-2.0
Author: Saulius Beinorius
Author-email: saulius.beinorius@gmail.com
Maintainer: Saulius Beinorius
Maintainer-email: saulius.beinorius@gmail.com
Requires-Python: >=3.7,<4.0
Classifier: License :: OSI Approved :: Apache Software License
Classifier: Programming Language :: Python :: 3
Classifier: Programming Language :: Python :: 3.7
Classifier: Programming Language :: Python :: 3.8
Classifier: Programming Language :: Python :: 3.9
Classifier: Programming Language :: Python :: 3.10
Classifier: Programming Language :: Python :: 3.11
Classifier: Topic :: Software Development :: Libraries :: Python Modules
Requires-Dist: pytest (>=5.2)
Project-URL: Repository, https://github.com/Barbora-Data-Science/pytest-integration-mark
